usernetes/__init__.py
usernetes/defaults.py
usernetes/instance.py
usernetes/runner.py
usernetes/utils.py
usernetes/version.py
usernetes/cli/__init__.py
usernetes/cli/clean.py
usernetes/cli/down.py
usernetes/cli/environment.py
usernetes/cli/start.py
usernetes/cli/wait.py
usernetes/config/__init__.py
usernetes/config/config.py
usernetes/logger/__init__.py
usernetes/logger/generate.py
usernetes/logger/logger.py
usernetes/src/.dockerignore
usernetes/src/.git
usernetes/src/.gitignore
usernetes/src/Dockerfile
usernetes/src/LICENSE
usernetes/src/Makefile
usernetes/src/README.md
usernetes/src/docker-compose.yaml
usernetes/src/kubeadm-config.yaml
usernetes/src/.github/workflows/main.yaml
usernetes/src/Dockerfile.d/etc_udev_rules.d_90-flannel.rules
usernetes/src/Dockerfile.d/u7s-entrypoint.sh
usernetes/src/Dockerfile.d/SHA256SUMS.d/cni-plugins-v1.5.1
usernetes/src/Makefile.d/check-preflight.sh
usernetes/src/Makefile.d/detect-container-engine.sh
usernetes/src/Makefile.d/node-subnet.sh
usernetes/src/Makefile.d/sync-external-ip.sh
usernetes/src/hack/README.md
usernetes/src/hack/create-cluster-lxd.sh
usernetes/src/hack/create-hosts-lxd.sh
usernetes/src/hack/test-smoke.sh
usernetes/src/init-host/README.md
usernetes/src/init-host/init-host.root.sh
usernetes/src/init-host/init-host.rootless.sh
usernetes/src/init-host/init-host.root.d/install-podman.sh
usernetes-0.0.11.dist-info/LICENSE
usernetes-0.0.11.dist-info/METADATA
usernetes-0.0.11.dist-info/NOTICE
usernetes-0.0.11.dist-info/WHEEL
usernetes-0.0.11.dist-info/entry_points.txt
usernetes-0.0.11.dist-info/top_level.txt
usernetes-0.0.11.dist-info/RECORD
