Metadata-Version: 2.1
Name: usernetes
Version: 0.0.11
Summary: Python wrapper for user-space Kubernetes 'usernetes'
Home-page: https://github.com/converged-computing/usernetes-python
Author: Vanessa Sochat
Author-email: vsoch@users.noreply.github.com
Maintainer: Vanessa Sochat
License: LICENSE
Keywords: cluster,orchestration,user-space kubernetes,kubernetes,compose
Classifier: Intended Audience :: Science/Research
Classifier: Intended Audience :: Developers
Classifier: License :: OSI Approved :: Mozilla Public License 2.0 (MPL 2.0)
Classifier: Programming Language :: C
Classifier: Programming Language :: Python
Classifier: Topic :: Software Development
Classifier: Topic :: Scientific/Engineering
Classifier: Operating System :: Unix
Classifier: Programming Language :: Python :: 3.11
License-File: LICENSE
License-File: NOTICE
Provides-Extra: all
Requires-Dist: pytest >=4.6.2 ; extra == 'all'
